{"type": "FeatureCollection", "features": [{"type": "Feature", "geometry": {"type": "Point", "coordinates": [-97.7600467, 35.4788152]}, "properties": {"description": "flock camera", "direction": "70", "man_made": "surveillance", "surveillance": "traffic", "surveillance:type": "ALPR", "surveillance:zone": "traffic"}}, {"type": "Feature", "geometry": {"type": "Point", "coordinates": [-97.7423559, 35.4791119]}, "properties": {"description": "Flock camera", "direction": "330", "man_made": "surveillance", "manufacturer": "Flock Safety", "operator": "Yukon Police", "surveillance": "traffic", "surveillance:type": "ALPR", "surveillance:zone": "traffic"}}, {"type": "Feature", "geometry": {"type": "Point", "coordinates": [-97.7591762, 35.4811814]}, "properties": {"description": "flock camera", "direction": "340", "man_made": "surveillance", "surveillance": "traffic", "surveillance:type": "ALPR", "surveillance:zone": "traffic"}}, {"type": "Feature", "geometry": {"type": "Point", "coordinates": [-97.7585153, 35.4811841]}, "properties": {"description": "flock camera", "direction": "30", "man_made": "surveillance", "surveillance": "traffic", "surveillance:type": "ALPR", "surveillance:zone": "traffic"}}, {"type": "Feature", "geometry": {"type": "Point", "coordinates": [-97.7584588, 35.483378]}, "properties": {"description": "flock camera", "direction": "160", "man_made": "surveillance", "surveillance": "traffic", "surveillance:type": "ALPR", "surveillance:zone": "traffic"}}, {"type": "Feature", "geometry": {"type": "Point", "coordinates": [-97.955087, 35.5479849]}, "properties": {"description": "Flock camera", "direction": "150", "man_made": "surveillance", "manufacturer": "Flock Safety", "surveillance": "traffic", "surveillance:type": "ALPR", "surveillance:zone": "traffic"}}, {"type": "Feature", "geometry": {"type": "Point", "coordinates": [-97.9725488, 35.510414]}, "properties": {"description": "Flock camera", "direction": "335", "man_made": "surveillance", "manufacturer": "Flock Safety", "surveillance": "traffic", "surveillance:type": "ALPR", "surveillance:zone": "traffic"}}, {"type": "Feature", "geometry": {"type": "Point", "coordinates": [-97.7451134, 35.6422583]}, "properties": {"camera:direction": "340", "camera:type": "fixed", "man_made": "surveillance", "manufacturer": "Flock Safety", "manufacturer:wikidata": "Q108485435", "surveillance": "traffic", "surveillance:type": "ALPR", "surveillance:zone": "traffic"}}, {"type": "Feature", "geometry": {"type": "Point", "coordinates": [-97.7453832, 35.6427366]}, "properties": {"direction": "145", "man_made": "surveillance", "manufacturer": "Flock Safety", "manufacturer:wikidata": "Q108485435", "surveillance": "traffic", "surveillance:type": "ALPR", "surveillance:zone": "traffic"}}, {"type": "Feature", "geometry": {"type": "Point", "coordinates": [-97.7604472, 35.4890569]}, "properties": {"camera:type": "fixed", "direction": "150", "man_made": "surveillance", "manufacturer": "Flock Safety", "manufacturer:wikidata": "Q108485435", "surveillance": "traffic", "surveillance:type": "ALPR"}}], "networks": []}