{"type": "FeatureCollection", "features": [{"type": "Feature", "geometry": {"type": "Point", "coordinates": [58.3945577, 37.9386187]}, "properties": {"id": 5121206621, "man_made": "surveillance", "data_source": "planet_osm"}}, {"type": "Feature", "geometry": {"type": "Point", "coordinates": [58.3946306, 37.9386869]}, "properties": {"id": 5121206622, "man_made": "surveillance", "data_source": "planet_osm"}}, {"type": "Feature", "geometry": {"type": "Point", "coordinates": [58.405529, 37.9455065]}, "properties": {"id": 5950582885, "man_made": "surveillance", "data_source": "planet_osm"}}, {"type": "Feature", "geometry": {"type": "Point", "coordinates": [58.3626439, 37.9009106]}, "properties": {"id": 6949161486, "man_made": "surveillance", "data_source": "planet_osm"}}], "networks": []}