{"type": "FeatureCollection", "features": [{"type": "Feature", "geometry": {"type": "Point", "coordinates": [-123.4973703, 47.9697534]}, "properties": {"camera:direction": "165", "camera:type": "fixed", "contact:webcam": "https://www.nps.gov/media/webcam/view.htm?id=81B46251-1DD8-B71B-0B29B9750DE273B5", "description": "Looking South from Hurricane Ridge toward the Lillian and Elwha River valleys.", "man_made": "surveillance", "name": "Hurricane Ridge", "operator": "Washington's National Park Fund", "operator:wikidata": "Q7971582", "surveillance": "webcam", "surveillance:type": "camera", "surveillance:zone": "nature"}}, {"type": "Feature", "geometry": {"type": "Point", "coordinates": [-123.4970573, 47.9699018]}, "properties": {"camera:direction": "75", "camera:type": "fixed", "contact:webcam": "https://www.nps.gov/media/webcam/view.htm?id=81B46260-1DD8-B71B-0B7A7B41BF33172A", "man_made": "surveillance", "name": "Hurricane Ridge Parking Lot", "operator": "Washington's National Park Fund", "operator:wikidata": "Q7971582", "surveillance": "webcam", "surveillance:type": "camera", "surveillance:zone": "traffic"}}], "networks": []}