{"type": "FeatureCollection", "features": [{"type": "Feature", "geometry": {"type": "Point", "coordinates": [-105.1589552, 41.0985721]}, "properties": {"camera:mount": "pole", "camera:type": "panning", "man_made": "surveillance", "name": "Harriman", "surveillance": "outdoor", "surveillance:type": "camera", "surveillance:zone": "traffic"}}, {"type": "Feature", "geometry": {"type": "Point", "coordinates": [-105.2096801, 41.0985898]}, "properties": {"camera:mount": "pole", "camera:type": "panning", "man_made": "surveillance", "name": "Remount", "surveillance": "outdoor", "surveillance:type": "camera", "surveillance:zone": "traffic"}}, {"type": "Feature", "geometry": {"type": "Point", "coordinates": [-105.2806876, 41.1179059]}, "properties": {"camera:mount": "pole", "camera:type": "dome", "man_made": "surveillance", "name": "Buford East", "surveillance": "outdoor", "surveillance:type": "camera", "surveillance:zone": "traffic"}}, {"type": "Feature", "geometry": {"type": "Point", "coordinates": [-105.3392449, 41.128293]}, "properties": {"camera:mount": "pole", "camera:type": "panning", "man_made": "surveillance", "name": "Lone Tree", "surveillance": "outdoor", "surveillance:type": "camera", "surveillance:zone": "traffic"}}, {"type": "Feature", "geometry": {"type": "Point", "coordinates": [-105.3841055, 41.1466223]}, "properties": {"camera:mount": "pole", "camera:type": "dome", "man_made": "surveillance", "name": "Vedauwoo", "surveillance": "outdoor", "surveillance:type": "camera", "surveillance:zone": "traffic"}}, {"type": "Feature", "geometry": {"type": "Point", "coordinates": [-105.4360207, 41.2019588]}, "properties": {"camera:mount": "pole", "camera:type": "dome", "man_made": "surveillance", "material": "metal", "name": "Summit East", "surveillance": "outdoor", "surveillance:type": "camera", "surveillance:zone": "traffic"}}, {"type": "Feature", "geometry": {"type": "Point", "coordinates": [-105.4372357, 41.2400419]}, "properties": {"camera:mount": "pole", "camera:type": "dome", "man_made": "surveillance", "material": "wood", "name": "Summit", "surveillance": "outdoor", "surveillance:type": "camera", "surveillance:zone": "traffic"}}, {"type": "Feature", "geometry": {"type": "Point", "coordinates": [-105.4241321, 41.1888493]}, "properties": {"camera:mount": "pole", "camera:type": "dome", "man_made": "surveillance", "name": "Summit Tavern", "surveillance": "outdoor", "surveillance:type": "camera", "surveillance:zone": "traffic"}}], "networks": []}