{"type": "FeatureCollection", "features": [{"type": "Feature", "geometry": {"type": "Point", "coordinates": [-75.2237412, 39.979783]}, "properties": {"man_made": "surveillance", "surveillance": "outdoor"}}, {"type": "Feature", "geometry": {"type": "Point", "coordinates": [-75.2241112, 39.979633]}, "properties": {"man_made": "surveillance", "surveillance": "outdoor"}}, {"type": "Feature", "geometry": {"type": "Point", "coordinates": [-75.2232656, 39.9781576]}, "properties": {"man_made": "surveillance", "surveillance": "outdoor"}}, {"type": "Feature", "geometry": {"type": "Point", "coordinates": [-75.2240207, 39.9797919]}, "properties": {"man_made": "surveillance", "surveillance": "outdoor"}}, {"type": "Feature", "geometry": {"type": "Point", "coordinates": [-75.233684, 39.9609535]}, "properties": {"camera:mount": "roof", "camera:type": "dome", "man_made": "surveillance", "surveillance": "outdoor", "surveillance:type": "camera"}}, {"type": "Feature", "geometry": {"type": "Point", "coordinates": [-75.2340964, 39.9610054]}, "properties": {"camera:mount": "wall", "man_made": "surveillance", "surveillance": "outdoor", "surveillance:type": "camera"}}, {"type": "Feature", "geometry": {"type": "Point", "coordinates": [-75.2340792, 39.9610047]}, "properties": {"camera:mount": "wall", "man_made": "surveillance", "surveillance": "outdoor", "surveillance:type": "camera"}}, {"type": "Feature", "geometry": {"type": "Point", "coordinates": [-75.1513089, 39.9707162]}, "properties": {"camera:direction": "-55", "camera:mount": "roof", "camera:type": "fixed", "man_made": "surveillance", "surveillance": "outdoor", "surveillance:type": "camera"}}, {"type": "Feature", "geometry": {"type": "Point", "coordinates": [-75.1513039, 39.97071]}, "properties": {"camera:direction": "127", "camera:mount": "roof", "camera:type": "fixed", "man_made": "surveillance", "surveillance:type": "camera"}}, {"type": "Feature", "geometry": {"type": "Point", "coordinates": [-75.1198204, 40.0380659]}, "properties": {"camera:mount": "wall", "camera:type": "dome", "man_made": "surveillance", "surveillance": "outdoor", "surveillance:type": "camera"}}, {"type": "Feature", "geometry": {"type": "Point", "coordinates": [-75.1204455, 40.0354649]}, "properties": {"camera:mount": "roof", "camera:type": "dome", "man_made": "surveillance", "surveillance": "outdoor", "surveillance:type": "camera"}}, {"type": "Feature", "geometry": {"type": "Point", "coordinates": [-75.2153958, 39.965581]}, "properties": {"camera:mount": "pole", "camera:type": "dome", "man_made": "surveillance", "surveillance": "public", "surveillance:type": "camera", "surveillance:zone": "town"}}, {"type": "Feature", "geometry": {"type": "Point", "coordinates": [-75.2174687, 39.9592898]}, "properties": {"camera:mount": "roof", "camera:type": "dome", "man_made": "surveillance", "surveillance": "outdoor", "surveillance:type": "camera"}}, {"type": "Feature", "geometry": {"type": "Point", "coordinates": [-75.2187364, 39.9597611]}, "properties": {"camera:direction": "-170", "camera:mount": "wall", "camera:type": "fixed", "man_made": "surveillance", "surveillance:type": "camera"}}, {"type": "Feature", "geometry": {"type": "Point", "coordinates": [-75.1705699, 39.963411]}, "properties": {"camera:mount": "wall", "camera:type": "dome", "man_made": "surveillance", "surveillance": "outdoor", "surveillance:type": "camera", "surveillance:zone": "parking"}}, {"type": "Feature", "geometry": {"type": "Point", "coordinates": [-75.1705862, 39.9634367]}, "properties": {"camera:direction": "340", "camera:mount": "wall", "camera:type": "fixed", "man_made": "surveillance", "surveillance": "outdoor", "surveillance:type": "camera", "surveillance:zone": "entrance"}}, {"type": "Feature", "geometry": {"type": "Point", "coordinates": [-75.2246094, 39.9784515]}, "properties": {"camera:mount": "roof", "camera:type": "dome", "man_made": "surveillance", "surveillance": "outdoor", "surveillance:type": "camera", "surveillance:zone": "parking"}}, {"type": "Feature", "geometry": {"type": "Point", "coordinates": [-75.2258219, 40.0234081]}, "properties": {"layer": "1", "location": "bridge", "man_made": "surveillance", "surveillance:type": "camera"}}, {"type": "Feature", "geometry": {"type": "Point", "coordinates": [-75.2271702, 40.027254]}, "properties": {"layer": "1", "location": "bridge", "man_made": "surveillance", "surveillance:type": "camera"}}, {"type": "Feature", "geometry": {"type": "Point", "coordinates": [-75.2261257, 40.0237429]}, "properties": {"layer": "1", "location": "bridge", "man_made": "surveillance", "surveillance:type": "camera"}}, {"type": "Feature", "geometry": {"type": "Point", "coordinates": [-75.2269027, 40.026636]}, "properties": {"layer": "1", "location": "bridge", "man_made": "surveillance", "surveillance:type": "camera"}}, {"type": "Feature", "geometry": {"type": "Point", "coordinates": [-75.2268221, 40.0262614]}, "properties": {"layer": "1", "location": "bridge", "man_made": "surveillance", "surveillance:type": "camera"}}, {"type": "Feature", "geometry": {"type": "Point", "coordinates": [-75.2263965, 40.0242405]}, "properties": {"layer": "1", "location": "bridge", "man_made": "surveillance", "surveillance:type": "camera"}}, {"type": "Feature", "geometry": {"type": "Point", "coordinates": [-75.2266516, 40.0253404]}, "properties": {"layer": "1", "location": "bridge", "man_made": "surveillance", "surveillance:type": "camera"}}, {"type": "Feature", "geometry": {"type": "Point", "coordinates": [-75.035375, 40.0748379]}, "properties": {"camera:direction": "130", "camera:mount": "pole", "camera:type": "fixed", "man_made": "surveillance", "surveillance": "red_light", "surveillance:type": "camera", "surveillance:zone": "traffic"}}, {"type": "Feature", "geometry": {"type": "Point", "coordinates": [-75.0345605, 40.0750527]}, "properties": {"camera:direction": "235", "camera:mount": "pole", "camera:type": "fixed", "man_made": "surveillance", "surveillance": "red_light", "surveillance:type": "camera", "surveillance:zone": "traffic"}}, {"type": "Feature", "geometry": {"type": "Point", "coordinates": [-75.0345448, 40.074997]}, "properties": {"camera:direction": "205", "camera:mount": "pole", "camera:type": "fixed", "man_made": "surveillance", "surveillance": "red_light", "surveillance:type": "camera", "surveillance:zone": "traffic"}}, {"type": "Feature", "geometry": {"type": "Point", "coordinates": [-75.0352525, 40.0737593]}, "properties": {"camera:direction": "65", "camera:mount": "pole", "camera:type": "fixed", "man_made": "surveillance", "surveillance": "red_light", "surveillance:type": "camera", "surveillance:zone": "traffic"}}, {"type": "Feature", "geometry": {"type": "Point", "coordinates": [-75.035261, 40.0737641]}, "properties": {"camera:direction": "25", "camera:mount": "pole", "camera:type": "fixed", "man_made": "surveillance", "surveillance": "red_light", "surveillance:type": "camera", "surveillance:zone": "traffic"}}, {"type": "Feature", "geometry": {"type": "Point", "coordinates": [-75.0343122, 40.0738493]}, "properties": {"camera:direction": "315", "camera:mount": "pole", "camera:type": "fixed", "man_made": "surveillance", "surveillance": "red_light", "surveillance:type": "camera", "surveillance:zone": "traffic"}}, {"type": "Feature", "geometry": {"type": "Point", "coordinates": [-75.2122191, 40.0309033]}, "properties": {"man_made": "surveillance", "surveillance:type": "camera"}}, {"type": "Feature", "geometry": {"type": "Point", "coordinates": [-75.2105705, 40.0291132]}, "properties": {"man_made": "surveillance", "surveillance:type": "camera"}}, {"type": "Feature", "geometry": {"type": "Point", "coordinates": [-75.2153606, 40.0043513]}, "properties": {"man_made": "surveillance", "surveillance:type": "camera"}}, {"type": "Feature", "geometry": {"type": "Point", "coordinates": [-75.2153534, 40.0043453]}, "properties": {"man_made": "surveillance", "surveillance:type": "camera"}}, {"type": "Feature", "geometry": {"type": "Point", "coordinates": [-75.1873964, 39.9630835]}, "properties": {"camera:mount": "pole", "camera:type": "fixed", "direction": "10", "man_made": "surveillance", "role": "device", "surveillance": "red_light", "surveillance:type": "camera", "surveillance:zone": "street"}}, {"type": "Feature", "geometry": {"type": "Point", "coordinates": [-75.187099, 39.9634762]}, "properties": {"camera:mount": "pole", "camera:type": "fixed", "direction": "250", "man_made": "surveillance", "role": "device", "surveillance": "red_light", "surveillance:type": "camera", "surveillance:zone": "street"}}, {"type": "Feature", "geometry": {"type": "Point", "coordinates": [-75.205139, 40.0282102]}, "properties": {"camera:direction": "325", "camera:mount": "pole", "camera:type": "fixed", "man_made": "surveillance", "surveillance": "red_light", "surveillance:type": "camera", "surveillance:zone": "traffic"}}, {"type": "Feature", "geometry": {"type": "Point", "coordinates": [-75.2061705, 40.0283715]}, "properties": {"camera:direction": "56", "camera:mount": "pole", "camera:type": "fixed", "man_made": "surveillance", "surveillance": "red_light", "surveillance:type": "camera", "surveillance:zone": "traffic"}}, {"type": "Feature", "geometry": {"type": "Point", "coordinates": [-75.206022, 40.0290515]}, "properties": {"camera:direction": "143", "camera:mount": "pole", "camera:type": "fixed", "man_made": "surveillance", "surveillance": "red_light", "surveillance:type": "camera", "surveillance:zone": "traffic"}}, {"type": "Feature", "geometry": {"type": "Point", "coordinates": [-75.2050685, 40.0289454]}, "properties": {"camera:direction": "233", "camera:mount": "pole", "camera:type": "fixed", "man_made": "surveillance", "surveillance": "red_light", "surveillance:type": "camera", "surveillance:zone": "traffic"}}, {"type": "Feature", "geometry": {"type": "Point", "coordinates": [-75.1809525, 39.9514638]}, "properties": {"covered": "yes", "man_made": "surveillance", "surveillance:type": "camera"}}, {"type": "Feature", "geometry": {"type": "Point", "coordinates": [-75.1865565, 39.9463269]}, "properties": {"man_made": "surveillance", "surveillance:type": "camera"}}, {"type": "Feature", "geometry": {"type": "Point", "coordinates": [-75.1825306, 39.965508]}, "properties": {"man_made": "surveillance", "surveillance:type": "camera"}}, {"type": "Feature", "geometry": {"type": "Point", "coordinates": [-75.1800292, 39.9653447]}, "properties": {"man_made": "surveillance"}}, {"type": "Feature", "geometry": {"type": "Point", "coordinates": [-75.1798436, 39.9659949]}, "properties": {"man_made": "surveillance", "surveillance:type": "camera"}}, {"type": "Feature", "geometry": {"type": "Point", "coordinates": [-75.1802205, 39.9662673]}, "properties": {"man_made": "surveillance", "surveillance:type": "camera"}}, {"type": "Feature", "geometry": {"type": "Point", "coordinates": [-75.1938386, 39.9416385]}, "properties": {"man_made": "surveillance", "surveillance:type": "camera"}}, {"type": "Feature", "geometry": {"type": "Point", "coordinates": [-75.1937848, 39.9416123]}, "properties": {"man_made": "surveillance", "surveillance:type": "camera"}}, {"type": "Feature", "geometry": {"type": "Point", "coordinates": [-75.1927243, 39.9419]}, "properties": {"man_made": "surveillance", "surveillance:type": "camera"}}, {"type": "Feature", "geometry": {"type": "Point", "coordinates": [-75.1926707, 39.9418737]}, "properties": {"man_made": "surveillance", "surveillance:type": "camera"}}, {"type": "Feature", "geometry": {"type": "Point", "coordinates": [-75.1972592, 39.9416533]}, "properties": {"man_made": "surveillance", "surveillance:type": "camera"}}, {"type": "Feature", "geometry": {"type": "Point", "coordinates": [-75.2160836, 40.0051952]}, "properties": {"camera:mount": "wall", "man_made": "surveillance", "surveillance:type": "camera"}}, {"type": "Feature", "geometry": {"type": "Point", "coordinates": [-75.2161276, 40.0052407]}, "properties": {"camera:mount": "wall", "man_made": "surveillance", "surveillance:type": "camera"}}, {"type": "Feature", "geometry": {"type": "Point", "coordinates": [-75.1470613, 39.9758065]}, "properties": {"camera:mount": "pole", "camera:type": "dome", "check_date": "2025-07-17", "man_made": "surveillance", "surveillance": "outdoor", "surveillance:type": "camera"}}, {"type": "Feature", "geometry": {"type": "Point", "coordinates": [-75.146794, 39.9771998]}, "properties": {"camera:mount": "pole", "camera:type": "dome", "man_made": "surveillance", "surveillance": "public", "surveillance:type": "camera"}}, {"type": "Feature", "geometry": {"type": "Point", "coordinates": [-75.0711231, 40.1291336]}, "properties": {"man_made": "surveillance", "surveillance:type": "camera"}}, {"type": "Feature", "geometry": {"type": "Point", "coordinates": [-75.1407389, 40.1558256]}, "properties": {"brand": "Flock Safety", "check_date": "2025-08-01", "description": "Camera and its solar panel are black, located on a pre-existing white pole. Installed out of reach, roughly 20-30ft up.\nFlock camera points into the parking lot from Welsh rd, ID-ing and profiling anything that that passes in its sight.", "direction": "4", "height": "6-9", "man_made": "surveillance", "manufacturer": "Flock Safety", "material": "plastic", "name": "Flock Camera", "official_name": "Flock Safety", "surveillance": "camera,_ai,_alpr,_flock,_police,_public,_outdoor", "surveillance:type": "ALPR", "surveillance:zone": "entrance,_parking"}}, {"type": "Feature", "geometry": {"type": "Point", "coordinates": [-75.1416708, 40.1562457]}, "properties": {"brand": "Flock", "check_date": "2025-08-01", "description": "Camera and its solar panel are black, located on a dedicated short black pole. Installed within reach, roughly 10ft up.\nFlock camera points into the parking lot from Welsh rd, ID-ing & profiling anything that passes in front of it.", "direction": "0", "height": "3", "man_made": "surveillance", "manufacturer": "Flock Safety", "material": "plastic", "name": "Flock Safety, Flock,", "official_name": "Flock Safety", "surveillance": "camera,_ai,_flock,_alpr,_police,_public,_outdoor", "surveillance:type": "ALPR", "surveillance:zone": "entrance"}}, {"type": "Feature", "geometry": {"type": "Point", "coordinates": [-75.1486476, 40.1599358]}, "properties": {"check_date": "2025-08-19", "description": "Black Flock camera w/ solar panel, placed about 10-15ft up, on a black lightpost. It points at the Sprouts market and into that parking lot vicinity, ID-ing & profiling anything in sight. Camera may be hidden behind flag; solar panel still visible.", "direction": "195", "man_made": "surveillance", "manufacturer": "Flock Safety", "material": "plastic", "name": "Flock Camera", "official_name": "Flock Safety", "start_date": "2025-06-18", "surveillance": "flock,_alpr,_public,_outdoor,_ai,_police", "surveillance:type": "ALPR", "surveillance:zone": "parking,_entrance"}}, {"type": "Feature", "geometry": {"type": "Point", "coordinates": [-75.1470935, 40.1587127]}, "properties": {"check_date": "2025-06-19", "description": "Black Flock camera w/ solar panel, placed about 10-15ft up, on a black lightpost. It points down Dryden Road away from Welsh, ID-ing & profiling anything in sight. Camera hidden by flag, solar panel visible.", "direction": "195", "man_made": "surveillance", "manufacturer": "Flock Safety", "material": "plastic", "name": "Flock camera, ALPR", "surveillance": "flock,_alpr,_public,_outdoor,_police,_ai", "surveillance:type": "ALPR", "surveillance:zone": "road,_entrance"}}, {"type": "Feature", "geometry": {"type": "Point", "coordinates": [-75.1513711, 40.1587322]}, "properties": {"check_date": "2025-08-13", "description": "Black Flock camera w/ solar panel, placed about 10-15ft up, on a black lightpost. It points at the Sprouts market and into that parking lot vicinity, ID-ing & profiling anything in sight. Camera may be hidden behind flag; solar panel still visible.", "direction": "85", "man_made": "surveillance", "manufacturer": "Flock Safety", "material": "plastic", "name": "Flock Camera", "official_name": "Flock Safety", "surveillance": "flock,_alpr,_public,_outdoor,_ai,_police", "surveillance:type": "ALPR", "surveillance:zone": "parking,_entrance"}}, {"type": "Feature", "geometry": {"type": "Point", "coordinates": [-75.1473093, 39.9743741]}, "properties": {"camera:mount": "pole", "camera:type": "dome", "man_made": "surveillance", "surveillance:type": "camera", "surveillance:zone": "street"}}, {"type": "Feature", "geometry": {"type": "Point", "coordinates": [-75.1457516, 39.9741691]}, "properties": {"camera:mount": "pole", "camera:type": "dome", "man_made": "surveillance", "surveillance": "outdoor", "surveillance:type": "camera", "surveillance:zone": "street"}}, {"type": "Feature", "geometry": {"type": "Point", "coordinates": [-75.2092566, 39.9536]}, "properties": {"camera:type": "fixed", "man_made": "surveillance", "surveillance:type": "ALPR"}}, {"type": "Feature", "geometry": {"type": "Point", "coordinates": [-75.2226989, 39.9782658]}, "properties": {"camera:type": "fixed", "man_made": "surveillance", "surveillance:type": "ALPR"}}, {"type": "Feature", "geometry": {"type": "Point", "coordinates": [-75.1266176, 40.164771]}, "properties": {"brand": "Flock", "check_date": "2025-08-20", "description": "Camera and its solar panel are black, located on a dedicated black pole. Installed just out of reach, roughly 15ft up.\nFlock camera points into the parking lot from Home Depot drive, ID-ing & profiling anything in sight.", "direction": "270", "height": "3", "man_made": "surveillance", "manufacturer": "Flock Safety", "material": "plastic", "name": "Flock Camera", "official_name": "Flock Safety", "surveillance": "camera,_ai,_flock,_police,_outdoor,_public", "surveillance:type": "ALPR", "surveillance:zone": "entrance,_parking"}}, {"type": "Feature", "geometry": {"type": "Point", "coordinates": [-75.1266049, 40.1647455]}, "properties": {"brand": "Flock", "check_date": "2025-08-020", "description": "Camera and its solar panel are black, located on a dedicated black pole. Installed just out of reach, roughly 15ft up. Dragnet surveillance Flock camera points into the parking lot of Home Depot, ID's & profiles anything in sight.", "direction": "180", "height": "3", "man_made": "surveillance", "manufacturer": "Flock Safety", "material": "plastic", "name": "Flock Camera", "official_name": "Flock Safety", "surveillance": "camera,_ai,_flock,_police,_outdoor,_public", "surveillance:type": "ALPR", "surveillance:zone": "entrance,_parking"}}, {"type": "Feature", "geometry": {"type": "Point", "coordinates": [-75.098198, 40.0285804]}, "properties": {"brand": "Flock", "check_date": "2025-5-020", "description": "Camera and its solar panel are black, located on a dedicated black pole. Installed just out of reach, roughly 10-15ft up.\nFlock camera points into the parking lot of Home Depot, ID-ing & profiling any car that enters here or passes in front of it.", "direction": "310", "height": "3", "man_made": "surveillance", "manufacturer": "Flock Safety", "material": "plastic", "name": "Flock Camera", "surveillance": "camera,_ai,_flock,_police", "surveillance:type": "ALPR", "surveillance:zone": "entrance"}}, {"type": "Feature", "geometry": {"type": "Point", "coordinates": [-75.0991106, 40.0298768]}, "properties": {"brand": "Flock", "check_date": "2025-5-020", "description": "Camera and its solar panel are black, located on a tall light post. Uncertain camera model. About 15ft up", "direction": "120", "height": "3", "man_made": "surveillance", "manufacturer": "Flock Safety", "material": "plastic", "name": "Flock Camera", "surveillance": "camera,", "surveillance:type": "ALPR", "surveillance:zone": "parking"}}, {"type": "Feature", "geometry": {"type": "Point", "coordinates": [-75.0990475, 40.030495]}, "properties": {"brand": "Flock", "check_date": "2025-08-20", "description": "Camera and its solar panel are black, located on a dedicated black pole. Installed just out of reach, roughly 10-15ft up.\nFlock camera points into the parking lot of Home Depot, ID-ing & profiling any car that enters here or passes in front of it.", "direction": "120", "height": "3", "man_made": "surveillance", "manufacturer": "Flock Safety", "material": "plastic", "name": "Flock Camera", "surveillance": "camera,_ai,_flock,_police", "surveillance:type": "ALPR", "surveillance:zone": "entrance"}}, {"type": "Feature", "geometry": {"type": "Point", "coordinates": [-75.0986713, 40.0302316]}, "properties": {"camera:mount": "ceiling", "camera:type": "dome", "man_made": "surveillance", "surveillance": "public,_parking,_security", "surveillance:type": "camera", "surveillance:zone": "parking_lot,_building"}}, {"type": "Feature", "geometry": {"type": "Point", "coordinates": [-75.101991, 40.0323063]}, "properties": {"brand": "Flock", "check_date": "2025-5-020", "description": "Camera and its solar panel are black, located on a dedicated black pole. Installed just out of reach, roughly 10-15ft up.\nFlock camera points into the parking lot towards Kid City, ID-ing & profiling any car that enters here or passes in front of it.", "direction": "45", "height": "3", "man_made": "surveillance", "manufacturer": "Flock Safety", "material": "plastic", "name": "Flock Camera", "surveillance": "camera,_ai,_flock,_police", "surveillance:type": "ALPR", "surveillance:zone": "entrance"}}, {"type": "Feature", "geometry": {"type": "Point", "coordinates": [-75.1019612, 40.0322949]}, "properties": {"brand": "Flock", "check_date": "2025-5-020", "description": "Camera and its solar panel are black, located on a dedicated black pole. Installed just out of reach, roughly 10-15ft up.\nFlock camera points into the parking lot towards Home Depot, ID-ing & profiling any car that enters here or passes in front of it.", "direction": "120", "height": "3", "man_made": "surveillance", "manufacturer": "Flock Safety", "material": "plastic", "name": "Flock Camera", "surveillance": "camera,_ai,_flock,_police", "surveillance:type": "ALPR", "surveillance:zone": "entrance,_parking"}}, {"type": "Feature", "geometry": {"type": "Point", "coordinates": [-75.0987605, 40.0294046]}, "properties": {"camera:mount": "pole", "camera:type": "dome", "check_date": "2025-08-10", "description": "Tall white pole mounted on a mobile platform, with a large solar panel closer to the ground. Several dome cameras high up, unknown if A.I. May contain a horn, which case this is likely for annoying/deterring homeless who may sleep here.", "man_made": "surveillance", "manufacturer": "LVT", "name": "Police Tower", "surveillance": "public,_outdoor,_parking", "surveillance:type": "camera", "surveillance:zone": "parking"}}, {"type": "Feature", "geometry": {"type": "Point", "coordinates": [-75.1530279, 40.0753911]}, "properties": {"brand": "Flock", "check_date": "2025-6-020", "description": "Camera and its solar panel are black, located on a dedicated black pole. Installed just out of reach, roughly 10-15ft up.\nFlock camera points into the parking lot around Home Depot, ID-ing & profiling anything that enters here or passes in front of it.", "direction": "200", "height": "3", "man_made": "surveillance", "manufacturer": "Flock Safety", "material": "plastic", "name": "Flock Camera", "surveillance": "camera,_ai,_flock,_police", "surveillance:type": "ALPR", "surveillance:zone": "entrance,_parking"}}, {"type": "Feature", "geometry": {"type": "Point", "coordinates": [-75.1531955, 40.0752323]}, "properties": {"man_made": "surveillance", "surveillance:type": "camera"}}, {"type": "Feature", "geometry": {"type": "Point", "coordinates": [-75.1538898, 40.0743927]}, "properties": {"brand": "Flock", "check_date": "2025-6-020", "description": "Camera and its solar panel are black, located on a dedicated black pole. Installed just out of reach, roughly 10-15ft up.\nFlock camera points into the parking lot towards Home Depot, ID-ing & profiling anything that enters here or passes in front of it.", "direction": "35", "height": "3", "man_made": "surveillance", "manufacturer": "Flock Safety", "material": "plastic", "name": "Flock Camera", "surveillance": "camera,_ai,_flock,_police", "surveillance:type": "ALPR", "surveillance:zone": "entrance,_parking"}}, {"type": "Feature", "geometry": {"type": "Point", "coordinates": [-75.2213167, 40.1546943]}, "properties": {"camera:direction": "190", "man_made": "surveillance", "surveillance:type": "camera"}}, {"type": "Feature", "geometry": {"type": "Point", "coordinates": [-74.9871478, 39.9524736]}, "properties": {"direction": "40", "man_made": "surveillance", "surveillance:type": "ALPR"}}, {"type": "Feature", "geometry": {"type": "Point", "coordinates": [-74.9865648, 39.9526791]}, "properties": {"direction": "250", "man_made": "surveillance", "surveillance:type": "ALPR"}}, {"type": "Feature", "geometry": {"type": "Point", "coordinates": [-74.9849005, 39.9488732]}, "properties": {"direction": "40", "man_made": "surveillance", "surveillance:type": "ALPR"}}, {"type": "Feature", "geometry": {"type": "Point", "coordinates": [-74.9845685, 39.9492179]}, "properties": {"direction": "205", "man_made": "surveillance", "surveillance:type": "ALPR"}}, {"type": "Feature", "geometry": {"type": "Point", "coordinates": [-74.9854161, 39.9498169]}, "properties": {"fixme": "Verify location - can be seen from Route 73 GSV (Aug. 2023)", "man_made": "surveillance", "surveillance:type": "ALPR"}}, {"type": "Feature", "geometry": {"type": "Point", "coordinates": [-74.9842274, 39.9471762]}, "properties": {"direction": "10", "man_made": "surveillance", "surveillance:type": "ALPR"}}, {"type": "Feature", "geometry": {"type": "Point", "coordinates": [-74.9842135, 39.9474327]}, "properties": {"direction": "2000", "man_made": "surveillance", "surveillance:type": "ALPR"}}, {"type": "Feature", "geometry": {"type": "Point", "coordinates": [-74.9840912, 39.9473551]}, "properties": {"direction": "10", "man_made": "surveillance", "surveillance:type": "ALPR"}}, {"type": "Feature", "geometry": {"type": "Point", "coordinates": [-75.0919762, 39.9919481]}, "properties": {"camera:type": "fixed", "direction": "80", "man_made": "surveillance", "manufacturer": "Flock Safety", "manufacturer:wikidata": "Q108485435", "surveillance:type": "ALPR"}}, {"type": "Feature", "geometry": {"type": "Point", "coordinates": [-75.0926028, 39.9927166]}, "properties": {"camera:type": "fixed", "direction": "30", "man_made": "surveillance", "manufacturer": "Flock Safety", "manufacturer:wikidata": "Q108485435", "surveillance:type": "ALPR"}}, {"type": "Feature", "geometry": {"type": "Point", "coordinates": [-75.091064, 39.996765]}, "properties": {"camera:type": "fixed", "direction": "310", "man_made": "surveillance", "manufacturer": "Flock Safety", "manufacturer:wikidata": "Q108485435", "surveillance:type": "ALPR"}}, {"type": "Feature", "geometry": {"type": "Point", "coordinates": [-75.092767, 39.9976591]}, "properties": {"camera:type": "fixed", "direction": "160", "man_made": "surveillance", "manufacturer": "Flock Safety", "manufacturer:wikidata": "Q108485435", "surveillance:type": "ALPR"}}, {"type": "Feature", "geometry": {"type": "Point", "coordinates": [-75.0565847, 39.9204604]}, "properties": {"camera:type": "fixed", "direction": "175", "man_made": "surveillance", "manufacturer": "Flock Safety", "manufacturer:wikidata": "Q108485435", "surveillance": "traffic", "surveillance:type": "ALPR", "surveillance:zone": "traffic"}}, {"type": "Feature", "geometry": {"type": "Point", "coordinates": [-74.9437887, 40.0196046]}, "properties": {"check_date": "2025-11-08", "direction": "130", "man_made": "surveillance", "manufacturer": "Flock Safety", "note": "Estimated location as seen from Fairview Blvd", "surveillance:type": "ALPR"}}, {"type": "Feature", "geometry": {"type": "Point", "coordinates": [-74.8919677, 40.0478672]}, "properties": {"direction": "340", "man_made": "surveillance", "surveillance:type": "ALPR"}}, {"type": "Feature", "geometry": {"type": "Point", "coordinates": [-74.8922288, 40.0474565]}, "properties": {"direction": "150", "man_made": "surveillance", "surveillance:type": "ALPR"}}, {"type": "Feature", "geometry": {"type": "Point", "coordinates": [-74.8923303, 40.0475304]}, "properties": {"description": "Attached to traffic signal pole", "direction": "60", "man_made": "surveillance", "surveillance:type": "ALPR"}}, {"type": "Feature", "geometry": {"type": "Point", "coordinates": [-75.0552214, 39.9176483]}, "properties": {"camera:type": "fixed", "direction": "90", "man_made": "surveillance", "manufacturer": "Flock Safety", "manufacturer:wikidata": "Q108485435", "surveillance:type": "ALPR"}}, {"type": "Feature", "geometry": {"type": "Point", "coordinates": [-75.0284322, 39.9438652]}, "properties": {"camera:type": "fixed", "direction": "80", "man_made": "surveillance", "manufacturer": "Flock Safety", "manufacturer:wikidata": "Q108485435", "surveillance:type": "ALPR"}}, {"type": "Feature", "geometry": {"type": "Point", "coordinates": [-75.0258562, 39.9390937]}, "properties": {"camera:type": "fixed", "direction": "325", "man_made": "surveillance", "manufacturer": "Flock Safety", "manufacturer:wikidata": "Q108485435", "surveillance:type": "ALPR"}}, {"type": "Feature", "geometry": {"type": "Point", "coordinates": [-75.0394727, 39.922873]}, "properties": {"camera:type": "fixed", "direction": "135", "man_made": "surveillance", "manufacturer": "Flock Safety", "manufacturer:wikidata": "Q108485435", "surveillance:type": "ALPR"}}, {"type": "Feature", "geometry": {"type": "Point", "coordinates": [-75.038787, 39.922608]}, "properties": {"camera:type": "fixed", "direction": "270", "man_made": "surveillance", "manufacturer": "Flock Safety", "manufacturer:wikidata": "Q108485435", "surveillance:type": "ALPR"}}], "networks": []}