{"type": "FeatureCollection", "features": [{"type": "Feature", "geometry": {"type": "Point", "coordinates": [30.0761185, 59.8518548]}, "properties": {"id": 3083052555, "camera:mount": "pole", "camera:type": "fixed", "man_made": "surveillance", "note": "NOT A SPEED CAMERA! OBSERVATION CAMERA ONLY!", "surveillance": "outdoor", "surveillance:type": "camera", "surveillance:zone": "traffic", "data_source": "planet_osm"}}, {"type": "Feature", "geometry": {"type": "Point", "coordinates": [30.0761166, 59.8517864]}, "properties": {"id": 3083052556, "camera:mount": "pole", "camera:type": "fixed", "man_made": "surveillance", "note": "NOT A SPEED CAMERA! OBSERVATION CAMERA ONLY!", "surveillance": "outdoor", "surveillance:type": "camera", "surveillance:zone": "traffic", "data_source": "planet_osm"}}], "networks": []}